sweatDB/__init__.py
sweatDB/sweatDB.py
sweatDB-2.0.9.dist-info/METADATA
sweatDB-2.0.9.dist-info/WHEEL
sweatDB-2.0.9.dist-info/top_level.txt
sweatDB-2.0.9.dist-info/RECORD
